{
    "('To: University of California, Berkeley', 'From: Sacramento City College')": [
        "Electrical Engineering & Computer Sciences, Lower Division B.S.",
        {
            "MATH 1A": "MATH 400",
            "MATH 1B": "MATH 401",
            "MATH 53": "MATH 402",
            "MATH 54": "MATH 420",
            "PHYSICS 7A": "PHYS 410",
            "PHYSICS 7B": "PHYS 420",
            "ENGLISH R1A": "ENGWR 300",
            "ENGLISH R1B": "ENGWR 301",
            "ASTRON 7A": "No Course Articulated",
            "ASTRON 7B": "No Course Articulated",
            "BIOLOGY 1A": "BIOL 402",
            "BIOLOGY 1B": "BIOL 412",
            "CHEM 1A": "CHEM 400",
            "CHEM 1B": "CHEM 401",
            "CHEM 3A": "CHEM 420",
            "CHEM 3B": "CHEM 421",
            "MCELLBI 32": "BIOL 430",
            "PHYSICS 7C": "PHYS 430",
            "COMPSCI 61A": "No Course Articulated",
            "COMPSCI 61B": "CISP 430",
            "COMPSCI 61C": "No Course Articulated",
            "COMPSCI 70": "This course must be taken at the university after transfer",
            "EECS 16A": "No Course Articulated",
            "EECS 16B": "No Course Articulated"
        }
    ]
}